schecker/__init__.py
schecker/__main__.py
schecker/schecker.py
schecker-0.2.0.dist-info/LICENSE
schecker-0.2.0.dist-info/METADATA
schecker-0.2.0.dist-info/WHEEL
schecker-0.2.0.dist-info/entry_points.txt
schecker-0.2.0.dist-info/top_level.txt
schecker-0.2.0.dist-info/RECORD
