Metadata-Version: 2.1
Name: schecker
Version: 0.2.0
Summary: Simplify and wrap the use of clang-tidy and coccinelle
Home-page: http://github.com/hgn/schecker
Author: Hagen Paul Pfeifer
Author-email: hagen@jauu.net
License: MIT
Platform: UNKNOWN
Classifier: Development Status :: 4 - Beta
Classifier: Intended Audience :: Developers
Classifier: Topic :: Software Development :: Build Tools
Classifier: License :: OSI Approved :: MIT License
Classifier: Programming Language :: Python :: 3
Classifier: Programming Language :: Python :: 3.5
Classifier: Programming Language :: Python :: 3.6
Classifier: Programming Language :: Python :: 3.7
